joysticks/__init__.py
joysticks/__main__.py
joysticks/joysticks.py
joysticks-0.1.2.dist-info/LICENSE
joysticks-0.1.2.dist-info/METADATA
joysticks-0.1.2.dist-info/WHEEL
joysticks-0.1.2.dist-info/top_level.txt
joysticks-0.1.2.dist-info/RECORD
