Metadata-Version: 2.1
Name: joysticks
Version: 0.1.2
Summary: Parse joystick events in python
Home-page: UNKNOWN
Author: Matt Donahoe
Author-email: matt.donahoe@gmail.com
License: MIT
Platform: UNKNOWN
